{"content":"Title screen conventions: game logo/wordmark prominent (upper-center or center), small menu or single button prompt beneath, dynamic/atmospheric background matching game art direction; logo font style sets tone. Little formal literature — pattern evidence from Game UI Database Title Screen category and indie collections. Rebrand mid-development is common for indies; main expectation is consistency (title screen, HTML title, save-key naming, UI strings all updated).","source":"web","provider":"websearch","confidence":"LOW","fetched_at":"2026-07-05T08:23:39.580Z","ttl":86400000,"kind":"web"}
